AUTHORS.rst
CONTRIBUTING.rst
HISTORY.rst
LICENSE
MANIFEST.in
README.rst
setup.cfg
setup.py
django_south_central.egg-info/PKG-INFO
django_south_central.egg-info/SOURCES.txt
django_south_central.egg-info/dependency_links.txt
django_south_central.egg-info/not-zip-safe
django_south_central.egg-info/top_level.txt
south_central/__init__.py
south_central/migration.py
south_central/models.py
south_central/management/__init__.py
south_central/management/commands/__init__.py
south_central/management/commands/appmigration.py
south_central/management/commands/migrateapp.py
south_central/static/js/south_central.js
south_central/templates/south_central/base.html