Metadata-Version: 1.1
Name: django-south-central
Version: 0.1.0
Summary: Application state migration tool, inspired by South
Home-page: https://github.com/hiisi13/south_central
Author: Dmitry Kozhedubov
Author-email: dmitry-kozhedubov@yandex.ru
License: BSD
Keywords: south_central
Platform: UNKNOWN
Classifier: Development Status :: 2 - Pre-Alpha
Classifier: Framework :: Django
Classifier: Intended Audience :: Developers
Classifier: License :: OSI Approved :: BSD License
Classifier: Natural Language :: English
Classifier: Programming Language :: Python :: 2
Classifier: Programming Language :: Python :: 2.6
Classifier: Programming Language :: Python :: 2.7
Classifier: Programming Language :: Python :: 3
Classifier: Programming Language :: Python :: 3.3
